zipg/__init__.py
zipg/main.py
zipg-0.2.3.dist-info/entry_points.txt
zipg-0.2.3.dist-info/LICENSE
zipg-0.2.3.dist-info/METADATA
zipg-0.2.3.dist-info/WHEEL
zipg-0.2.3.dist-info/RECORD
